pycsbwrapper/__init__.py
pycsbwrapper/csb.py
pycsbwrapper-0.0.1.dist-info/licenses/LICENSE
pycsbwrapper-0.0.1.dist-info/METADATA
pycsbwrapper-0.0.1.dist-info/WHEEL
pycsbwrapper-0.0.1.dist-info/top_level.txt
pycsbwrapper-0.0.1.dist-info/RECORD
