Metadata-Version: 2.4
Name: pycsbwrapper
Version: 0.0.1
Summary: Python wrapper for Central Bureau of Statistics Republic of Latvia pxweb API
Author-email: Artūrs Luņevs <arturs.lunevs@gmail.com>
License: MIT
Project-URL: Homepage, https://github.com/arturslunevs/pycsbwrapper
Project-URL: Issues, https://github.com/arturslunevs/pycsbwrapper/issues
Classifier: Programming Language :: Python :: 3
Classifier: Operating System :: OS Independent
Requires-Python: >=3.7
License-File: LICENSE
Dynamic: license-file
